svbench/__init__.py
svbench/cli.py
svbench/io_tools.py
svbench/loaders.py
svbench/quant_tools.py
svbench/models/__init__.py
svbench-0.7.10.dist-info/LICENSE.md
svbench-0.7.10.dist-info/METADATA
svbench-0.7.10.dist-info/WHEEL
svbench-0.7.10.dist-info/entry_points.txt
svbench-0.7.10.dist-info/top_level.txt
svbench-0.7.10.dist-info/RECORD
