Metadata-Version: 2.1
Name: svbench
Version: 0.7.10
License: MIT
Requires-Python: >=3.7
License-File: LICENSE.md
Requires-Dist: numpy
Requires-Dist: pandas
Requires-Dist: networkx >=2.4
Requires-Dist: ncls
Requires-Dist: pyvcf3
Requires-Dist: matplotlib
Requires-Dist: click
